Backups_clientAPI/Copia.py
Backups_clientAPI/LlocDeCopies.py
Backups_clientAPI/Pandora.py
Backups_clientAPI/SynologyActive.py
Backups_clientAPI/SynologyHyper.py
Backups_clientAPI/__init__.py
Backups_clientAPI/__main__.py
Backups_clientAPI/mspbackup.py
Backups_clientAPI/utils.py
Backups_clientAPI_NPP-1.2.dist-info/LICENSE
Backups_clientAPI_NPP-1.2.dist-info/METADATA
Backups_clientAPI_NPP-1.2.dist-info/WHEEL
Backups_clientAPI_NPP-1.2.dist-info/entry_points.txt
Backups_clientAPI_NPP-1.2.dist-info/top_level.txt
Backups_clientAPI_NPP-1.2.dist-info/RECORD
